MANIFEST.in
README.md
setup.cfg
setup.py
SysScribe.egg-info/PKG-INFO
SysScribe.egg-info/SOURCES.txt
SysScribe.egg-info/dependency_links.txt
SysScribe.egg-info/top_level.txt
sysscribe/__init__.py
sysscribe/cpu.py
sysscribe/disk.py
sysscribe/memory.py
sysscribe/network.py
sysscribe/pci.py
sysscribe/system.py